sygaldry_cli/__init__.py
sygaldry_cli/config_manager.py
sygaldry_cli/main.py
sygaldry_cli/commands/__init__.py
sygaldry_cli/commands/add.py
sygaldry_cli/commands/build_cmd.py
sygaldry_cli/commands/docs.py
sygaldry_cli/commands/init_cmd.py
sygaldry_cli/commands/list_components.py
sygaldry_cli/commands/mcp_cmd.py
sygaldry_cli/commands/search.py
sygaldry_cli/commands/source.py
sygaldry_cli/core/__init__.py
sygaldry_cli/core/cache_manager.py
sygaldry_cli/core/component_manager.py
sygaldry_cli/core/known_llms.json
sygaldry_cli/core/models.py
sygaldry_cli/core/registry_handler.py
sygaldry_cli/core/utils.py
sygaldry_cli-0.1.0.dist-info/licenses/LICENSE
sygaldry_cli-0.1.0.dist-info/METADATA
sygaldry_cli-0.1.0.dist-info/WHEEL
sygaldry_cli-0.1.0.dist-info/entry_points.txt
sygaldry_cli-0.1.0.dist-info/top_level.txt
sygaldry_cli-0.1.0.dist-info/RECORD
