Metadata-Version: 2.4
Name: sygaldry-cli
Version: 0.1.0
Summary: Production-ready AI components that you can copy and paste into your apps
Author-email: greyhaven-ai <info@sygaldry.ai>
License: MIT
Project-URL: homepage, https://sygaldry.ai
Project-URL: repository, https://github.com/sygaldry-ai/sygaldry
Project-URL: documentation, https://sygaldry.ai/docs
Keywords: ai,llm,agents,tools,components,mirascope,lilypad
Classifier: Development Status :: 4 - Beta
Classifier: Intended Audience :: Developers
Classifier: Programming Language :: Python :: 3
Classifier: Programming Language :: Python :: 3.12
Classifier: Topic :: Software Development :: Libraries :: Python Modules
Classifier: Topic :: Scientific/Engineering :: Artificial Intelligence
Requires-Python: <3.13,>=3.12
License-File: LICENSE
Requires-Dist: typer[all]<0.13.0,>=0.12.3
Requires-Dist: httpx<0.28.0,>=0.27.0
Requires-Dist: pydantic<3.0.0,>=2.5.0
Requires-Dist: rich<14.0.0,>=13.0.0
Requires-Dist: platformdirs<5.0.0,>=4.0.0
Provides-Extra: dev
Requires-Dist: argcomplete<4.0.0,>=3.5.0; extra == "dev"
Requires-Dist: deptry<1.0.0,>=0.23.0; extra == "dev"
Requires-Dist: icecream<3.0.0,>=2.1.3; extra == "dev"
Requires-Dist: ipython<9.0.0,>=8.27.0; extra == "dev"
Requires-Dist: mypy<2.0.0,>=1.14.1; extra == "dev"
Requires-Dist: pyclean<4.0.0,>=3.0.0; extra == "dev"
Requires-Dist: pytest-asyncio<1.0.0,>=0.25.2; extra == "dev"
Requires-Dist: pytest-cov<7.0.0,>=6.0.0; extra == "dev"
Requires-Dist: pytest<9.0.0,>=8.3.4; extra == "dev"
Requires-Dist: rich<14.0.0,>=13.8.1; extra == "dev"
Requires-Dist: ruff>=0.9.5; extra == "dev"
Requires-Dist: mirascope>=1.24.0; extra == "dev"
Requires-Dist: lilypad-sdk>=0.1.0; extra == "dev"
Requires-Dist: aiofiles>=0.8.0; extra == "dev"
Requires-Dist: asyncpg>=0.29.0; extra == "dev"
Requires-Dist: beautifulsoup4>=4.12.0; extra == "dev"
Requires-Dist: duckduckgo-search>=3.8.0; extra == "dev"
Requires-Dist: exa-py>=1.0.0; extra == "dev"
Requires-Dist: firecrawl-py>=0.0.1; extra == "dev"
Requires-Dist: fuzzywuzzy>=0.18.0; extra == "dev"
Requires-Dist: GitPython>=3.1.0; extra == "dev"
Requires-Dist: jsonpath-ng>=1.6.0; extra == "dev"
Requires-Dist: lxml>=4.9.0; extra == "dev"
Requires-Dist: markdown>=3.5.0; extra == "dev"
Requires-Dist: pandas>=2.0.0; extra == "dev"
Requires-Dist: PyGithub>=2.1.0; extra == "dev"
Requires-Dist: PyPDF2>=3.0.0; extra == "dev"
Requires-Dist: python-docx>=1.0.0; extra == "dev"
Requires-Dist: python-frontmatter>=1.0.0; extra == "dev"
Requires-Dist: python-Levenshtein>=0.20.0; extra == "dev"
Requires-Dist: pyyaml>=6.0; extra == "dev"
Requires-Dist: youtube-transcript-api>=0.6.0; extra == "dev"
Requires-Dist: sqlalchemy>=2.0.0; extra == "dev"
Requires-Dist: psycopg2-binary>=2.9.0; extra == "dev"
Requires-Dist: alembic>=1.12.0; extra == "dev"
Provides-Extra: test
Requires-Dist: coverage<8.0.0,>=7.6.1; extra == "test"
Requires-Dist: hypothesis[cli]<7.0.0,>=6.112.1; extra == "test"
Requires-Dist: pytest<9.0.0,>=8.3.3; extra == "test"
Requires-Dist: pytest-asyncio<1.0.0,>=0.24.0; extra == "test"
Requires-Dist: pytest-cov>=6.1.1; extra == "test"
Requires-Dist: pytest-datafiles<4.0.0,>=3.0.0; extra == "test"
Requires-Dist: pytest-xdist<4.0.0,>=3.6.1; extra == "test"
Dynamic: license-file
